mlspace/__init__.py
mlspace/logger.py
mlspace/mlspace.py
mlspace/utils.py
mlspace/cli/__init__.py
mlspace/cli/create.py
mlspace/cli/mlspace.py
mlspace/cli/setup.py
mlspace/cli/start.py
mlspace/cli/stop.py
mlspace/dockerfiles/__init__.py
mlspace/dockerfiles/torch_gpu.py
mlspace/requirements/__init__.py
mlspace/requirements/base.py
mlspace/requirements/torch_gpu.py
mlspace/scripts/__init__.py
mlspace/scripts/base.py
mlspace/scripts/install_docker.py
mlspace/scripts/install_nvidia_docker.py
mlspace/scripts/install_nvidia_drivers.py
mlspace-0.0.5.dist-info/LICENSE
mlspace-0.0.5.dist-info/METADATA
mlspace-0.0.5.dist-info/WHEEL
mlspace-0.0.5.dist-info/entry_points.txt
mlspace-0.0.5.dist-info/top_level.txt
mlspace-0.0.5.dist-info/RECORD
