Metadata-Version: 2.1
Name: mlspace
Version: 0.0.5
Summary: MLSpace: no hassle machine learning and deep learning
Home-page: https://github.com/abhishekkrthakur/mlspace
Author: Abhishek Thakur
Author-email: abhishek4@gmail.com
License: Apache 2.0
Platform: linux
Platform: unix
Requires-Python: >3.5.2
License-File: LICENSE
